[
  {
    "eventA":"name1",
    "eventB":"name2",
    "corr":true
  }, {
  "eventA":"name3",
  "eventB":"name4",
  "corr":false
},{
  "eventA":"name33",
  "eventB":"name47",
  "corr":false
},{
  "eventA":"name166",
  "eventB":"name21",
  "corr":true
}, {
  "eventA":"name37",
  "eventB":"name48",
  "corr":false
},{
  "eventA":"name10",
  "eventB":"name20",
  "corr":true
},{
  "eventA":"name15",
  "eventB":"name24",
  "corr":true
}, {
  "eventA":"name32",
  "eventB":"name46",
  "corr":false
},{
  "eventA":"name18",
  "eventB":"name28",
  "corr":true
}, {
  "eventA":"name354",
  "eventB":"name49",
  "corr":true
},{
  "eventA":"name12",
  "eventB":"name22",
  "corr":true
}, {
  "eventA":"name13",
  "eventB":"name14",
  "corr":false
}, {
  "eventA":"Aname13",
  "eventB":"Tname14",
  "corr":true
}, {
  "eventA":"Ename13",
  "eventB":"Fname14",
  "corr":false
}, {
  "eventA":"@name13",
  "eventB":"Wname14",
  "corr":false
}, {
  "eventA":"Qname13",
  "eventB":"QQname14",
  "corr":true
}, {
  "eventA":"FFname13",
  "eventB":"Dname14",
  "corr":false
}, {
  "eventA":"EDname13",
  "eventB":"FGname14",
  "corr":true
}, {
  "eventA":"eenaddsafme13",
  "eventB":"eenagdsafme14",
  "corr":true
}, {
  "eventA":"enadmedsafdf13",
  "eventB":"enagmddsafsafe14",
  "corr":true
}, {
  "eventA":"anadmsedsfadsaf13",
  "eventB":"anagmsddsafasfe14",
  "corr":true
}, {
  "eventA":"bnadmfsafffe13",
  "eventB":"bnagmefffdsfff14",
  "corr":true
}, {
  "eventA":"anadmedsfdsaf13",
  "eventB":"anagmddsaasfe14",
  "corr":true
}, {
  "eventA":"bnadmdsafffe13",
  "eventB":"bnagefffdsafff14",
  "corr":true
}, {
  "eventA":"anadmedsfadsaf1f3",
  "eventB":"anagmddsafasffe14",
  "corr":true
}, {
  "eventA":"bnadmfdsafffe1f3",
  "eventB":"bnagmefffdsaffff14",
  "corr":true
}, {
  "eventA":"1@name13",
  "eventB":"2Wname14",
  "corr":false
}, {
  "eventA":"2Qname13",
  "eventB":"QQ1name14",
  "corr":true
}, {
  "eventA":"FFn2ame13",
  "eventB":"Dna3me14",
  "corr":false
}, {
  "eventA":"EDna1me13",
  "eventB":"FGna3me14",
  "corr":true
}, {
  "eventA":"eeee13",
  "eventB":"eend",
  "corr":false
},{
  "eventA":"@namfe13",
  "eventB":"Wnamfe14",
  "corr":false
}, {
  "eventA":"Qndamfe13",
  "eventB":"2name14",
  "corr":true
}, {
  "eventA":"88name13",
  "eventB":"77ame14",
  "corr":false
}, {
  "eventA":"E3Dfname13",
  "eventB":"FG3fname14",
  "corr":false
}, {
  "eventA":"esfadme13",
  "eventB":"edsafdsafme14",
  "corr":true
}

]